Workbook

Sheet Catálogo
A1: ID | B1: Título | C1: Autor | D1: Editorial | E1: Categoría | F1: Foto | G1: Estado de lectura | H1: Ubicación | I1: Notas
A2: 1 | B2: Toulouse-Lautrec | C2: Hajo Düchting | D2: Könemann | E2: Arte | F2: 12
A3: 2 | B3: Angela Merkel | C3: Ana Carbajosa | E3: Biografías | F3: 16
A4: 3 | B4: Leonardo da Vinci: La biografía | C4: Walter Isaacson | E4: Biografías | F4: 16
A5: 4 | B5: Rubik | C5: Ernő Rubik | D5: Blackie Books | E5: Biografías | F5: 16
A6: 5 | B6: Steve Jobs: Lecciones de liderazgo | C6: Walter Isaacson | E6: Biografías | F6: 7
A7: 6 | B7: Una tierra prometida | C7: Barack Obama | E7: Biografías | F7: 16
A8: 7 | B8: Aromas del mundo | C8: Harold McGee | D8: Debate | E8: Ciencia y divulgación | F8: 14
A9: 8 | B9: El código secreto | D9: Evergreen | E9: Ciencia y divulgación | F9: 14
A10: 9 | B10: El espejismo de Dios | C10: Richard Dawkins | D10: Espasa | E10: Ciencia y divulgación | F10: 6
A11: 10 | B11: El futuro de nuestra mente | C11: Michio Kaku | D11: Debate | E11: Ciencia y divulgación | F11: 21
A12: 11 | B12: El hombre que calculaba | C12: Malba Tahan | D12: Lucemar | E12: Ciencia y divulgación | F12: 12
A13: 12 | B13: El inconcebible universo | C13: José Gordon | E13: Ciencia y divulgación | F13: 6
A14: 13 | B14: La conquista de la actualidad | C14: Steven Johnson | D14: Granica | E14: Ciencia y divulgación | F14: 6 | I14: Confirmar autor
A15: 14 | B15: La física del futuro | C15: Michio Kaku | D15: Debate | E15: Ciencia y divulgación | F15: 12
A16: 15 | B16: La magia de las matemáticas | D16: RBA | E16: Ciencia y divulgación | F16: 12
A17: 16 | B17: La proporción áurea | C17: Mario Livio | E17: Ciencia y divulgación | F17: 11
A18: 17 | B18: La singularidad está más cerca | C18: Ray Kurzweil | E18: Ciencia y divulgación | F18: 10
A19: 18 | B19: Los científicos y el mundo | C19: Robert P. Crease | D19: Crítica | E19: Ciencia y divulgación | F19: 6
A20: 19 | B20: Mentes geniales | C20: Mario de la Piedra Walter | D20: Debate | E20: Ciencia y divulgación | F20: 6
A21: 20 | B21: Nexus | C21: Yuval Noah Harari | D21: Debate | E21: Ciencia y divulgación | F21: 6
A22: 21 | B22: Odorama | C22: Federico Kukso | D22: Taurus | E22: Ciencia y divulgación | F22: 14
A23: 22 | B23: Programados para crear | C23: Marcus du Sautoy | E23: Ciencia y divulgación | F23: 18
A24: 23 | B24: Comunícate, cautiva y convence | C24: Gaby Vargas | E24: Comunicación y marca personal | F24: 9
A25: 24 | B25: Cómo ganar amigos e influir sobre las personas | C25: Dale Carnegie | E25: Comunicación y marca personal | F25: 9
A26: 25 | B26: Cómo hablar bien en público e influir sobre las personas de negocios | C26: Dale Carnegie | E26: Comunicación y marca personal | F26: 9
A27: 26 | B27: Cómo vender su marca personal | C27: Raquel Gómez H. | E27: Comunicación y marca personal | F27: 9
A28: 27 | B28: El poder del lenguaje sin palabras | C28: Bárbara Tijerina | E28: Comunicación y marca personal | F28: 9
A29: 28 | B29: Habla para influenciar | C29: Brian Tracy | D29: Grijalbo | E29: Comunicación y marca personal | F29: 8
A30: 29 | B30: Hable como en TED | C30: Carmine Gallo | E30: Comunicación y marca personal | F30: 10
A31: 30 | B31: Ideas que pegan | C31: Chip Heath, Dan Heath | E31: Comunicación y marca personal | F31: 18
A32: 31 | B32: Imparable | C32: Sebastián Lora | D32: EXMA | E32: Comunicación y marca personal | F32: 9
A33: 32 | B33: Influencia y persuasión | C33: Guías HBR | E33: Comunicación y marca personal | F33: 13
A34: 33 | B34: La comunicación no verbal | C34: Flora Davis | E34: Comunicación y marca personal | F34: 22
A35: 34 | B35: La isla de los 5 faros | C35: Ferran Ramon-Cortés | E35: Comunicación y marca personal | F35: 8
A36: 35 | B36: Marketing personal | C36: Jorge E. Prieto Herrera | E36: Comunicación y marca personal | F36: 9
A37: 36 | B37: Neuro oratoria | C37: Jürgen Klaric | E37: Comunicación y marca personal | F37: 16
A38: 37 | B38: No me hables en ese tono | C38: Ricardo Gómez | E38: Comunicación y marca personal | F38: 11
A39: 38 | B39: Piensa rápido, habla mejor | C39: Matt Abrahams | D39: Océano | E39: Comunicación y marca personal | F39: 11
A40: 39 | B40: Storytelling contigo | D40: Knaflic | E40: Comunicación y marca personal | F40: 9 | I40: Confirmar autor
A41: 40 | B41: Sé tu marca personal | C41: Claudia Palacio | E41: Comunicación y marca personal | F41: 9
A42: 41 | B42: Todo sobre la imagen del éxito | C42: Gaby Vargas | E42: Comunicación y marca personal | F42: 9
A43: 42 | B43: Usa tu derecho a presumir | C43: Karim Raymond | D43: PanHouse | E43: Comunicación y marca personal | F43: 9
A44: 43 | B44: Visibilidad infinita | C44: Andrea Liévano | E44: Comunicación y marca personal | F44: 9
A45: 44 | B45: ¡Salte con la tuya! | C45: Álvaro Gordoa | E45: Comunicación y marca personal | F45: 3
A46: 45 | B46: Crea: Una guía poco ortodoxa | C46: Tony Fadell | D46: Grijalbo | E46: Creatividad e innovación | F46: 15
A47: 46 | B47: El acto de crear | C47: Rick Rubin | E47: Creatividad e innovación | F47: 13
A48: 47 | B48: El espíritu creativo | C48: Daniel Goleman, Paul Kaufman, Michael Ray | E48: Creatividad e innovación | F48: 22
A49: 48 | B49: El secreto de la innovación | C49: Alejandro Ambrad Chalela | E49: Creatividad e innovación | F49: 17
A50: 49 | B50: Flujo de ideas | C50: Jeremy Utley, Perry Klebahn | E50: Creatividad e innovación | F50: 9
A51: 50 | B51: La chispa creativa | C51: Agustín Fuentes | D51: Ariel | E51: Creatividad e innovación | F51: 18
A52: 51 | B52: Libera tu magia | C52: Elizabeth Gilbert | D52: Aguilar | E52: Creatividad e innovación | F52: 7
A53: 52 | B53: LIT: Enciende tu cerebro | C53: Jeff Karp, Teresa Barker | E53: Creatividad e innovación | F53: 15
A54: 53 | B54: Originales | C54: Adam Grant | E54: Creatividad e innovación | F54: 17
A55: 54 | B55: Proceso creativo | C55: Eduardo Salles | E55: Creatividad e innovación | F55: 15
A56: 55 | B56: Roba como un artista | C56: Austin Kleon | D56: Aguilar | E56: Creatividad e innovación | F56: 13
A57: 56 | B57: Big Data con Python | C57: Rafael Caballero, Enrique Martín, Adrián Riesco | E57: Datos y tecnología | F57: 19
A58: 57 | B58: Datanomics | C58: Paloma Llaneza | E58: Datos y tecnología | F58: 19
A59: 58 | B59: Esclavos del algoritmo | C59: Laura G. de Rivera | D59: Debate | E59: Datos y tecnología | F59: 10
A60: 59 | B60: Inteligencia de negocios y analítica de datos | C60: Luis Joyanes | E60: Datos y tecnología | F60: 19
A61: 60 | B61: La invasión de los robots | C61: Xavier Sala i Martín | E61: Datos y tecnología | F61: 17
A62: 61 | B62: ¡Sálvese quien pueda! | C62: Andrés Oppenheimer | D62: Debate | E62: Datos y tecnología | F62: 19
A63: 62 | B63: Derecho territorial y urbano | C63: Gloria Henao González y otros | E63: Derecho | F63: 16
A64: 63 | B64: 1000 citas que invitan a pensar | C64: Antoni Bolinches | E64: Desarrollo personal | F64: 12
A65: 64 | B65: Caminando con mi mente | C65: Santiago Zapata | E65: Desarrollo personal | F65: 8 | I65: Confirmar título
A66: 65 | B66: Crea tu suerte | C66: Gay Hendricks, Carol Kline | D66: Aguilar | E66: Desarrollo personal | F66: 18
A67: 66 | B67: Cree lo increíble, logra lo imposible | C67: Nir Eyal, Julie Li | E67: Desarrollo personal | F67: 24
A68: 67 | B68: Cuando las arañas tejen juntas pueden atar a un león | E68: Desarrollo personal | F68: 16 | I68: Confirmar autor
A69: 68 | B69: Cómo dejar de ser tu peor enemigo | C69: Alba Cardalda | D69: Vergara | E69: Desarrollo personal | F69: 11
A70: 69 | B70: Cómo hacer que te pasen cosas buenas | C70: Marian Rojas Estapé | D70: Espasa | E70: Desarrollo personal | F70: 7
A71: 70 | B71: El arte de escuchar | C71: Julia Cameron | E71: Desarrollo personal | F71: 8
A72: 71 | B72: El arte de no amargarse la vida | C72: Rafael Santandreu | E72: Desarrollo personal | F72: 7
A73: 72 | B73: El arte de no reaccionar | C73: Ryushun Kusanagi | E73: Desarrollo personal | F73: 2
A74: 73 | B74: El poder de la gratitud | C74: Sofía Spaggiari | E74: Desarrollo personal | F74: 3
A75: 74 | B75: El viaje a la felicidad | C75: Eduardo Punset | D75: Booket | E75: Desarrollo personal | F75: 23
A76: 75 | B76: Encuentra tu persona vitamina | C76: Marian Rojas Estapé | D76: Espasa | E76: Desarrollo personal | F76: 7
A77: 76 | B77: Felices | C77: Elsa Punset | E77: Desarrollo personal | F77: 23
A78: 77 | B78: Felicidad a prueba de oficinas | C78: Sylvia Ramírez | E78: Desarrollo personal | F78: 19
A79: 78 | B79: Haz lo que importa | C79: Oso Trava | E79: Desarrollo personal | F79: 9
A80: 79 | B80: La auténtica felicidad | C80: Martin E. P. Seligman | D80: Zeta | E80: Desarrollo personal | F80: 23
A81: 80 | B81: La búsqueda de la felicidad | C81: Tal Ben-Shahar | E81: Desarrollo personal | F81: 23
A82: 81 | B82: La ciencia de la felicidad | C82: Sonja Lyubomirsky | E82: Desarrollo personal | F82: 23
A83: 82 | B83: La industria de la felicidad | C83: William Davies | E83: Desarrollo personal | F83: 23
A84: 83 | B84: La segunda mitad | C84: Diego Bernardini | E84: Desarrollo personal | F84: 10
A85: 84 | B85: La teoría Let Them | C85: Mel Robbins | E85: Desarrollo personal | F85: 2
A86: 85 | B86: Las mujeres inteligentes siempre consiguen lo que quieren | E86: Desarrollo personal | F86: 8
A87: 86 | B87: Libere la felicidad en el trabajo | C87: Jennifer Moss | D87: 3R Editores | E87: Desarrollo personal | F87: 23
A88: 87 | B88: Los hábitos de la buena suerte | C88: Verónica de Andrés | E88: Desarrollo personal | F88: 18
A89: 88 | B89: Manifiesto de felicidad | E89: Desarrollo personal | F89: 23 | I89: Confirmar autor
A90: 89 | B90: Misión felicidad | C90: María Elvira Pombo Marchand | D90: Diana | E90: Desarrollo personal | F90: 23
A91: 90 | B91: Mujeres imparables | C91: Sara Mesa | D91: Aguilar | E91: Desarrollo personal | F91: 3 | I91: Confirmar título/autor
A92: 91 | B92: Objetivo: felicidad | C92: Gretchen Rubin | D92: books4pocket | E92: Desarrollo personal | F92: 23
A93: 92 | B93: Ojalá me hubieran dicho esto antes | D93: Sancho BBDO | E93: Desarrollo personal | F93: 22 | I93: Confirmar autor
A94: 93 | B94: Recupera tu mente, reconquista tu vida | C94: Marian Rojas Estapé | D94: Espasa | E94: Desarrollo personal | F94: 7
A95: 94 | B95: Recupera tu poder | C95: Rut Nieves | E95: Desarrollo personal | F95: 8
A96: 95 | B96: Si lo crees, lo creas | C96: Brian Tracy, Christina Stein | D96: Aguilar | E96: Desarrollo personal | F96: 10
A97: 96 | B97: Sé un algoritmo irrepetible | C97: Daniela Violi | E97: Desarrollo personal | F97: 8
A98: 97 | B98: The Algebra of Happiness | C98: Scott Galloway | E98: Desarrollo personal | F98: 12
A99: 98 | B99: Think Pink | C99: Ecequiel Barricart | E99: Desarrollo personal | F99: 7
A100: 99 | B100: Tu mentalidad buena suerte | C100: Álex Rovira | E100: Desarrollo personal | F100: 7
...

Sheet Resumen
A1: Categoría | B1: Cantidad
A2: Arte | B2: =COUNTIF(Catálogo!$E$2:$E$316,A2)
A3: Biografías | B3: =COUNTIF(Catálogo!$E$2:$E$316,A3)
A4: Ciencia y divulgación | B4: =COUNTIF(Catálogo!$E$2:$E$316,A4)
A5: Comunicación y marca personal | B5: =COUNTIF(Catálogo!$E$2:$E$316,A5)
A6: Creatividad e innovación | B6: =COUNTIF(Catálogo!$E$2:$E$316,A6)
A7: Datos y tecnología | B7: =COUNTIF(Catálogo!$E$2:$E$316,A7)
A8: Derecho | B8: =COUNTIF(Catálogo!$E$2:$E$316,A8)
A9: Desarrollo personal | B9: =COUNTIF(Catálogo!$E$2:$E$316,A9)
A10: Diseño | B10: =COUNTIF(Catálogo!$E$2:$E$316,A10)
A11: Economía y decisiones | B11: =COUNTIF(Catálogo!$E$2:$E$316,A11)
A12: Ensayo | B12: =COUNTIF(Catálogo!$E$2:$E$316,A12)
A13: Espiritualidad | B13: =COUNTIF(Catálogo!$E$2:$E$316,A13)
... A30: Sin identificar | B30: =COUNTIF(Catálogo!$E$2:$E$316,A30)
A31: TOTAL | B31: =SUM(B2:B30)
